LICENSE
README.md
setup.cfg
setup.py
trademasterntu/__init__.py
trademasterntu.egg-info/PKG-INFO
trademasterntu.egg-info/SOURCES.txt
trademasterntu.egg-info/dependency_links.txt
trademasterntu.egg-info/requires.txt
trademasterntu.egg-info/top_level.txt
trademasterntu/agents/__init__.py
trademasterntu/agents/builder.py
trademasterntu/agents/custom.py
trademasterntu/agents/algorithmic_trading/__init__.py
trademasterntu/agents/algorithmic_trading/dqn.py
trademasterntu/agents/high_frequency_trading/__init__.py
trademasterntu/agents/high_frequency_trading/ddqn.py
trademasterntu/agents/order_execution/__init__.py
trademasterntu/agents/order_execution/eteo.py
trademasterntu/agents/order_execution/pd.py
trademasterntu/agents/portfolio_management/__init__.py
trademasterntu/agents/portfolio_management/deeptrader.py
trademasterntu/agents/portfolio_management/eiie.py
trademasterntu/agents/portfolio_management/investor_imitator.py
trademasterntu/collector/__init__.py
trademasterntu/collector/binance.py
trademasterntu/collector/builder.py
trademasterntu/collector/custom.py
trademasterntu/collector/helper/__init__.py
trademasterntu/collector/helper/celery_app.py
trademasterntu/collector/helper/celery_config.py
trademasterntu/collector/helper/pika_connection.py
trademasterntu/collector/helper/run_celery.py
trademasterntu/collector/helper/websocket_consumer.py
trademasterntu/collector/helper/websocket_producer.py
trademasterntu/datasets/__init__.py
trademasterntu/datasets/builder.py
trademasterntu/datasets/custom.py
trademasterntu/datasets/algorithmic_trading/__init__.py
trademasterntu/datasets/algorithmic_trading/dataset.py
trademasterntu/datasets/high_frequency_trading/__init__.py
trademasterntu/datasets/high_frequency_trading/dataset.py
trademasterntu/datasets/order_execution/__init__.py
trademasterntu/datasets/order_execution/dataset.py
trademasterntu/datasets/portfolio_management/__init__.py
trademasterntu/datasets/portfolio_management/dataset.py
trademasterntu/environments/__init__.py
trademasterntu/environments/builder.py
trademasterntu/environments/custom.py
trademasterntu/environments/algorithmic_trading/__init__.py
